base_conversion_kit/__init__.py
base_conversion_kit/base_conversion_kit.py
base_conversion_kit-1.0.7.dist-info/LICENSE
base_conversion_kit-1.0.7.dist-info/METADATA
base_conversion_kit-1.0.7.dist-info/WHEEL
base_conversion_kit-1.0.7.dist-info/top_level.txt
base_conversion_kit-1.0.7.dist-info/RECORD
