Metadata-Version: 2.1
Name: base-conversion-kit
Version: 1.0.7
Summary: Perform operations with numbers in different bases
Home-page: https://github.com/porfanid/base-conversion-kit
Author: porfanid
Author-email: pavlos@orfanidis.net.gr
License: UNKNOWN
Project-URL: Funding, https://ko-fi.com/porfanid
Project-URL: Source, https://github.com/porfanid/base-conversion-kit
Project-URL: Documentation, https://base-conversion-kit.readthedocs.io/
Project-URL: Tracker, https://github.com/porfanid/base-conversion-kit/issues
Project-URL: Say Thanks!, https://saythanks.io/to/porfanid
Keywords: base,conversion,kit,base,convert,numbers,add,multiply,subtract,Number Converter,Base Conversion,Numeric Operations,Number System Converter,Decimal to Binary,Decimal to Hexadecimal,Base Conversion Tool,Number Base Calculator,Binary Math Operations,Hexadecimal Arithmetic,Binary Converter,Number Base Converter,Base Conversion App,Numeric Base Operations,Decimal Arithmetic,Hex Converter,Number Base Transform,Number Base Manipulation,Binary Subtraction,Decimal Multiplication,Base Conversion
Platform: UNKNOWN
Requires-Python: >=3.6
Requires-Dist: markdown
